OCP.cpython-311-darwin.so
cadquery_ocp_arm_test.dylibs/libGLEW.2.1.0.dylib
cadquery_ocp_arm_test.dylibs/libIex.31.3.2.2.dylib
cadquery_ocp_arm_test.dylibs/libIlmThread.31.3.2.2.dylib
cadquery_ocp_arm_test.dylibs/libImath.29.10.0.dylib
cadquery_ocp_arm_test.dylibs/libLerc.4.dylib
cadquery_ocp_arm_test.dylibs/libOpenEXR.31.3.2.2.dylib
cadquery_ocp_arm_test.dylibs/libOpenEXRCore.31.3.2.2.dylib
cadquery_ocp_arm_test.dylibs/libTKBO.7.7.2.dylib
cadquery_ocp_arm_test.dylibs/libTKBRep.7.7.2.dylib
cadquery_ocp_arm_test.dylibs/libTKBin.7.7.2.dylib
cadquery_ocp_arm_test.dylibs/libTKBinL.7.7.2.dylib
cadquery_ocp_arm_test.dylibs/libTKBinTObj.7.7.2.dylib
cadquery_ocp_arm_test.dylibs/libTKBinXCAF.7.7.2.dylib
cadquery_ocp_arm_test.dylibs/libTKBool.7.7.2.dylib
cadquery_ocp_arm_test.dylibs/libTKCAF.7.7.2.dylib
cadquery_ocp_arm_test.dylibs/libTKCDF.7.7.2.dylib
cadquery_ocp_arm_test.dylibs/libTKFeat.7.7.2.dylib
cadquery_ocp_arm_test.dylibs/libTKFillet.7.7.2.dylib
cadquery_ocp_arm_test.dylibs/libTKG2d.7.7.2.dylib
cadquery_ocp_arm_test.dylibs/libTKG3d.7.7.2.dylib
cadquery_ocp_arm_test.dylibs/libTKGeomAlgo.7.7.2.dylib
cadquery_ocp_arm_test.dylibs/libTKGeomBase.7.7.2.dylib
cadquery_ocp_arm_test.dylibs/libTKHLR.7.7.2.dylib
cadquery_ocp_arm_test.dylibs/libTKIGES.7.7.2.dylib
cadquery_ocp_arm_test.dylibs/libTKIVtk.7.7.2.dylib
cadquery_ocp_arm_test.dylibs/libTKLCAF.7.7.2.dylib
cadquery_ocp_arm_test.dylibs/libTKMath.7.7.2.dylib
cadquery_ocp_arm_test.dylibs/libTKMesh.7.7.2.dylib
cadquery_ocp_arm_test.dylibs/libTKMeshVS.7.7.2.dylib
cadquery_ocp_arm_test.dylibs/libTKOffset.7.7.2.dylib
cadquery_ocp_arm_test.dylibs/libTKOpenGl.7.7.2.dylib
cadquery_ocp_arm_test.dylibs/libTKPrim.7.7.2.dylib
cadquery_ocp_arm_test.dylibs/libTKRWMesh.7.7.2.dylib
cadquery_ocp_arm_test.dylibs/libTKSTEP.7.7.2.dylib
cadquery_ocp_arm_test.dylibs/libTKSTEP209.7.7.2.dylib
cadquery_ocp_arm_test.dylibs/libTKSTEPAttr.7.7.2.dylib
cadquery_ocp_arm_test.dylibs/libTKSTEPBase.7.7.2.dylib
cadquery_ocp_arm_test-7.7.2.1.dist-info/LICENSE
cadquery_ocp_arm_test-7.7.2.1.dist-info/LICENSES_bundled
cadquery_ocp_arm_test-7.7.2.1.dist-info/METADATA
cadquery_ocp_arm_test-7.7.2.1.dist-info/WHEEL
cadquery_ocp_arm_test-7.7.2.1.dist-info/dependency_links.txt
cadquery_ocp_arm_test-7.7.2.1.dist-info/top_level.txt
cadquery_ocp_arm_test-7.7.2.1.dist-info/RECORD
