Metadata-Version: 2.1
Name: cadquery-ocp-arm-test
Version: 7.7.2.1
Summary: OCP wheel with shared library dependencies bundled.
Home-page: https://github.com/CadQuery/OCP
Download-URL: https://github.com/jmwright/ocp-build-system/releases
Author: adam-urbanczyk, fp473 (wheel generation), roipoussiere (wheel generation)
Classifier: Development Status :: 4 - Beta
Classifier: Intended Audience :: Developers
Classifier: Intended Audience :: Science/Research
Classifier: License :: OSI Approved :: Apache Software License
Classifier: Operating System :: POSIX
Classifier: Operating System :: MacOS
Classifier: Operating System :: Unix
Classifier: Programming Language :: Python
Classifier: Topic :: Software Development :: Libraries :: Python Modules
Classifier: Topic :: Scientific/Engineering
License-File: LICENSE
Requires-Dist: vtk ==9.2.6
